npl/__init__.py
npl/logging_config.py
npl/calculators/__init__.py
npl/calculators/base_calculator.py
npl/calculators/energy_calculator.py
npl/calculators/parameters.py
npl/calculators/top_calculator.py
npl/core/__init__.py
npl/core/adsorption.py
npl/core/atom_wrapper.py
npl/core/base_nanoparticle.py
npl/core/nanoparticle.py
npl/core/neighbor_list.py
npl/core/profiler.py
npl/descriptors/__init__.py
npl/descriptors/global_feature_classifier.py
npl/descriptors/local_environment_calculator.py
npl/descriptors/local_environment_feature_classifier.py
npl/monte_carlo/__init__.py
npl/monte_carlo/monte_carlo.py
npl/monte_carlo/monte_carlo_etop.py
npl/monte_carlo/monte_carlo_global_features.py
npl/monte_carlo/random_exchange_operator.py
npl/monte_carlo/random_exchange_operator_etop.py
npl/monte_carlo/ensembles/__init__.py
npl/monte_carlo/ensembles/base_ensemble.py
npl/monte_carlo/ensembles/canonical_ensemble.py
npl/monte_carlo/ensembles/grand_canonical_ensemble.py
npl/monte_carlo/ensembles/replica_exchange.py
npl/monte_carlo/mc_moves/__init__.py
npl/monte_carlo/mc_moves/mc_moves.py
npl/optimization/__init__.py
npl/optimization/go_search.py
npl/optimization/basin_hopping/__init__.py
npl/optimization/basin_hopping/basin_hopping.py
npl/optimization/genetic_algoritm/ConvexHull.py
npl/optimization/genetic_algoritm/CutAndSpliceOperator.py
npl/optimization/genetic_algoritm/ExchangeOperator.py
npl/optimization/genetic_algoritm/LocalOptimizationOperator.py
npl/optimization/genetic_algoritm/MutationOperator.py
npl/optimization/genetic_algoritm/NichedPopulation.py
npl/optimization/genetic_algoritm/SingleParticleGA.py
npl/optimization/genetic_algoritm/__init__.py
npl/optimization/local_optimization/__init__.py
npl/optimization/local_optimization/garbage_exchange_operator.py
npl/optimization/local_optimization/guided_exchange_operator.py
npl/optimization/local_optimization/local_optimization.py
npl/utils/__init__.py
npl/utils/cutting_plane_utilities.py
npl/utils/math_modules.py
npl-1.0.4.dist-info/LICENSE
npl-1.0.4.dist-info/METADATA
npl-1.0.4.dist-info/WHEEL
npl-1.0.4.dist-info/top_level.txt
npl-1.0.4.dist-info/RECORD
